kv_optkit-0.5.3.dist-info/licenses/LICENSE
kvopt/__init__.py
kvopt/__main__.py
kvopt/config.py
kvopt/plugin_manager.py
kvopt/policy_engine.py
kvopt/adapters/__init__.py
kvopt/adapters/base.py
kvopt/adapters/sim_adapter.py
kvopt/adapters/vllm_adapter.py
kvopt/agent/__init__.py
kvopt/agent/actions.py
kvopt/agent/executor.py
kvopt/agent/guard.py
kvopt/agent/planner.py
kvopt/agent/policy.py
kvopt/integrations/vllm/__init__.py
kvopt/integrations/vllm/adapters.py
kvopt/plugins/__init__.py
kvopt/plugins/kivi_plugin.py
kvopt/plugins/lmcache_plugin.py
kvopt/plugins/minikv_plugin.py
kvopt/server/main.py
kvopt/server/metrics.py
kvopt/server/routers/advisor.py
kvopt/server/routers/autopilot.py
kv_optkit-0.5.3.dist-info/METADATA
kv_optkit-0.5.3.dist-info/WHEEL
kv_optkit-0.5.3.dist-info/entry_points.txt
kv_optkit-0.5.3.dist-info/top_level.txt
kv_optkit-0.5.3.dist-info/RECORD
