Metadata-Version: 2.4
Name: kv-optkit
Version: 0.5.3
Summary: Optimization layer for LLM inference with KV-cache management
Author: KV-OptKit Maintainers
License: Apache-2.0
Project-URL: Homepage, https://github.com/archokshi/kv-optkit
Project-URL: Repository, https://github.com/archokshi/kv-optkit
Requires-Python: >=3.10
License-File: LICENSE
Requires-Dist: fastapi>=0.110
Requires-Dist: uvicorn>=0.23
Requires-Dist: pydantic>=2
Requires-Dist: PyYAML>=6
Requires-Dist: numpy>=1.24
Requires-Dist: prometheus-client>=0.16
Requires-Dist: matplotlib>=3.7
Requires-Dist: pandas>=2.0
Requires-Dist: requests>=2.31
Requires-Dist: httpx>=0.24
Dynamic: license-file
